{
  "jokes": [
    {"joke":"What's orange and sounds like a parrot? A Carrot."},
    {"joke":"I'm reading a book about anti-gravity. It's impossible to put down."},
    {"joke":"Why is it hard to make puns for kleptomaniacs? They are always taking things literally."},
    {"joke":"What do you call a cow with no legs? Ground beef"},
    {"joke":"Did you hear about the guy whose whole left side was cut off? He's all right now."},
    {"joke":"Did you hear about the Mexican train killer?  He had locomotives"},
    {"joke":"Two fish in a tank. One looks to the other and says 'Can you even drive this thing???'"},
    {"joke":"How many tickles does it take to tickle an octupus? Ten-tickles!"},
    {"joke":"What do you call a fake noodle?  An impasta"},
    {"joke":"Why did the cookie cry? It was feeling crumby."},
    {"joke":"Why do seagulls fly over the sea? Because they aren't bay-gulls!"},
    {"joke":"How did Darth Vader know what Luke was getting for Christmas? He felt his presents."},
    {"joke":"I used to be a banker, but I lost interest."},
    {"joke":"How did the hipster burn the roof of his mouth? He ate the pizza before it was cool."}
  ]
}